edwh_demo_plugin/__about__.py
edwh_demo_plugin/__init__.py
edwh_demo_plugin/demo_plugin.py
edwh_demo_plugin-0.1.2.dist-info/METADATA
edwh_demo_plugin-0.1.2.dist-info/WHEEL
edwh_demo_plugin-0.1.2.dist-info/entry_points.txt
edwh_demo_plugin-0.1.2.dist-info/licenses/LICENSE.txt
edwh_demo_plugin-0.1.2.dist-info/RECORD
