Metadata-Version: 2.4
Name: edwh-demo-plugin
Version: 0.1.2
Summary: Demo project with a plugin to be discovered from the edwh package
Project-URL: Documentation, https://github.com/educationwarehouse/edwh-demo-tasks-plugin#readme
Project-URL: Issues, https://github.com/educationwarehouse/edwh-demo-tasks-plugin/issues
Project-URL: Source, https://github.com/educationwarehouse/edwh-demo-tasks-plugin
Author-email: Remco Boerma <remco.b@educationwarehouse.nl>, Robin van der Noord <robin.vdn@educationwarehouse.nl>
License-Expression: MIT
License-File: LICENSE.txt
Keywords: edwh
Classifier: Development Status :: 4 - Beta
Classifier: Programming Language :: Python
Classifier: Programming Language :: Python :: 3.10
Classifier: Programming Language :: Python :: 3.11
Classifier: Programming Language :: Python :: 3.12
Classifier: Programming Language :: Python :: Implementation :: CPython
Classifier: Programming Language :: Python :: Implementation :: PyPy
Requires-Python: >=3.11
Requires-Dist: edwh
Provides-Extra: dev
Requires-Dist: black; extra == 'dev'
Requires-Dist: hatch; extra == 'dev'
Requires-Dist: python-semantic-release<8; extra == 'dev'
